{"nodes": [{"id": "e_unity_projects_matchthemall_copy_assets_match_them_all_scripts_gameplay_itemspotmanager_cs", "label": "ItemSpotManager.cs", "file_type": "code", "source_file": "Gameplay/ItemSpotManager.cs", "source_location": "L1"}, {"id": "gameplay_itemspotmanager_matchthemall_scripts", "label": "MatchThemAll.Scripts", "file_type": "code", "source_file": "Gameplay/ItemSpotManager.cs", "source_location": "L7"}, {"id": "gameplay_itemspotmanager_itemspotmanager", "label": "ItemSpotManager", "file_type": "code", "source_file": "Gameplay/ItemSpotManager.cs", "source_location": "L9"}, {"id": "monobehaviour", "label": "MonoBehaviour", "file_type": "code", "source_file": "", "source_location": ""}, {"id": "transform", "label": "Transform", "file_type": "code", "source_file": "Gameplay/ItemSpotManager.cs", "source_location": "L13"}, {"id": "itemspot", "label": "ItemSpot", "file_type": "code", "source_file": "Gameplay/ItemSpotManager.cs", "source_location": "L15"}, {"id": "int", "label": "int", "file_type": "code", "source_file": "Gameplay/ItemSpotManager.cs", "source_location": "L16"}, {"id": "vector3", "label": "Vector3", "file_type": "code", "source_file": "Gameplay/ItemSpotManager.cs", "source_location": "L18"}, {"id": "float", "label": "float", "file_type": "code", "source_file": "Gameplay/ItemSpotManager.cs", "source_location": "L22"}, {"id": "ease", "label": "Ease", "file_type": "code", "source_file": "Gameplay/ItemSpotManager.cs", "source_location": "L24"}, {"id": "action", "label": "Action", "file_type": "code", "source_file": "Gameplay/ItemSpotManager.cs", "source_location": "L26"}, {"id": "gameplay_itemspotmanager_itemspotmanager_awake", "label": ".Awake()", "file_type": "code", "source_file": "Gameplay/ItemSpotManager.cs", "source_location": "L29"}, {"id": "gameplay_itemspotmanager_itemspotmanager_start", "label": ".Start()", "file_type": "code", "source_file": "Gameplay/ItemSpotManager.cs", "source_location": "L45"}, {"id": "gameplay_itemspotmanager_itemspotmanager_ondestroy", "label": ".OnDestroy()", "file_type": "code", "source_file": "Gameplay/ItemSpotManager.cs", "source_location": "L51"}, {"id": "gameplay_itemspotmanager_itemspotmanager_onitembacktogame", "label": ".OnItemBackToGame()", "file_type": "code", "source_file": "Gameplay/ItemSpotManager.cs", "source_location": "L59"}, {"id": "item", "label": "Item", "file_type": "code", "source_file": "Gameplay/ItemSpotManager.cs", "source_location": "L59"}, {"id": "gameplay_itemspotmanager_itemspotmanager_onlevelspawned", "label": ".OnLevelSpawned()", "file_type": "code", "source_file": "Gameplay/ItemSpotManager.cs", "source_location": "L66"}, {"id": "level", "label": "Level", "file_type": "code", "source_file": "Gameplay/ItemSpotManager.cs", "source_location": "L66"}, {"id": "gameplay_itemspotmanager_itemspotmanager_resetspotsandstate", "label": ".ResetSpotsAndState()", "file_type": "code", "source_file": "Gameplay/ItemSpotManager.cs", "source_location": "L83"}, {"id": "gameplay_itemspotmanager_itemspotmanager_onitemclickedevent", "label": ".OnItemClickedEvent()", "file_type": "code", "source_file": "Gameplay/ItemSpotManager.cs", "source_location": "L102"}, {"id": "itemclickedevent", "label": "ItemClickedEvent", "file_type": "code", "source_file": "Gameplay/ItemSpotManager.cs", "source_location": "L102"}, {"id": "gameplay_itemspotmanager_itemspotmanager_handleitemclick", "label": ".HandleItemClick()", "file_type": "code", "source_file": "Gameplay/ItemSpotManager.cs", "source_location": "L116"}, {"id": "gameplay_itemspotmanager_itemspotmanager_getidealspotfor", "label": ".GetIdealSpotFor()", "file_type": "code", "source_file": "Gameplay/ItemSpotManager.cs", "source_location": "L126"}, {"id": "gameplay_itemspotmanager_itemspotmanager_trymoveitemtoidealspot", "label": ".TryMoveItemToIdealSpot()", "file_type": "code", "source_file": "Gameplay/ItemSpotManager.cs", "source_location": "L138"}, {"id": "gameplay_itemspotmanager_itemspotmanager_moveitemtospot", "label": ".MoveItemToSpot()", "file_type": "code", "source_file": "Gameplay/ItemSpotManager.cs", "source_location": "L149"}, {"id": "gameplay_itemspotmanager_itemspotmanager_handleitemreachedspot", "label": ".HandleItemReachedSpot()", "file_type": "code", "source_file": "Gameplay/ItemSpotManager.cs", "source_location": "L166"}, {"id": "gameplay_itemspotmanager_itemspotmanager_onmergestarted", "label": ".OnMergeStarted()", "file_type": "code", "source_file": "Gameplay/ItemSpotManager.cs", "source_location": "L176"}, {"id": "mergestartedevent", "label": "MergeStartedEvent", "file_type": "code", "source_file": "Gameplay/ItemSpotManager.cs", "source_location": "L176"}, {"id": "gameplay_itemspotmanager_itemspotmanager_moveallitemstotheleft", "label": ".MoveAllItemsToTheLeft()", "file_type": "code", "source_file": "Gameplay/ItemSpotManager.cs", "source_location": "L184"}, {"id": "gameplay_itemspotmanager_itemspotmanager_moveallitemstotherightfrom", "label": ".MoveAllItemsToTheRightFrom()", "file_type": "code", "source_file": "Gameplay/ItemSpotManager.cs", "source_location": "L210"}, {"id": "gameplay_itemspotmanager_itemspotmanager_moveitemtofirstfreespot", "label": ".MoveItemToFirstFreeSpot()", "file_type": "code", "source_file": "Gameplay/ItemSpotManager.cs", "source_location": "L264"}, {"id": "gameplay_itemspotmanager_itemspotmanager_getfreespot", "label": ".GetFreeSpot()", "file_type": "code", "source_file": "Gameplay/ItemSpotManager.cs", "source_location": "L279"}, {"id": "gameplay_itemspotmanager_itemspotmanager_isfreespotavailable", "label": ".IsFreeSpotAvailable()", "file_type": "code", "source_file": "Gameplay/ItemSpotManager.cs", "source_location": "L281"}, {"id": "gameplay_itemspotmanager_itemspotmanager_storespot", "label": ".StoreSpot()", "file_type": "code", "source_file": "Gameplay/ItemSpotManager.cs", "source_location": "L283"}, {"id": "gameplay_itemspotmanager_itemspotmanager_getrandomoccupiedspot", "label": ".GetRandomOccupiedSpot()", "file_type": "code", "source_file": "Gameplay/ItemSpotManager.cs", "source_location": "L290"}, {"id": "gameplay_itemspotmanager_itemspotmanager_hasitemonboard", "label": ".HasItemOnBoard()", "file_type": "code", "source_file": "Gameplay/ItemSpotManager.cs", "source_location": "L299"}, {"id": "eitemname", "label": "EItemName", "file_type": "code", "source_file": "Gameplay/ItemSpotManager.cs", "source_location": "L299"}, {"id": "gameplay_itemspotmanager_itemspotmanager_getitemsonboard", "label": ".GetItemsOnBoard()", "file_type": "code", "source_file": "Gameplay/ItemSpotManager.cs", "source_location": "L309"}, {"id": "list", "label": "List", "file_type": "code", "source_file": "Gameplay/ItemSpotManager.cs", "source_location": "L309"}, {"id": "gameplay_itemspotmanager_itemspotmanager_getoccupieditemtypes", "label": ".GetOccupiedItemTypes()", "file_type": "code", "source_file": "Gameplay/ItemSpotManager.cs", "source_location": "L320"}, {"id": "ienumerable", "label": "IEnumerable", "file_type": "code", "source_file": "Gameplay/ItemSpotManager.cs", "source_location": "L320"}, {"id": "gameplay_itemspotmanager_itemspotmanager_isboardfullandnoitemsmoving", "label": ".IsBoardFullAndNoItemsMoving()", "file_type": "code", "source_file": "Gameplay/ItemSpotManager.cs", "source_location": "L331"}, {"id": "gameplay_itemspotmanager_itemspotmanager_getbesthintitems", "label": ".GetBestHintItems()", "file_type": "code", "source_file": "Gameplay/ItemSpotManager.cs", "source_location": "L341"}], "edges": [{"source": "e_unity_projects_matchthemall_copy_assets_match_them_all_scripts_gameplay_itemspotmanager_cs", "target": "system", "relation": "imports", "context": "import", "confidence": "EXTRACTED", "source_file": "Gameplay/ItemSpotManager.cs", "source_location": "L1", "weight": 1.0}, {"source": "e_unity_projects_matchthemall_copy_assets_match_them_all_scripts_gameplay_itemspotmanager_cs", "target": "generic", "relation": "imports", "context": "import", "confidence": "EXTRACTED", "source_file": "Gameplay/ItemSpotManager.cs", "source_location": "L2", "weight": 1.0}, {"source": "e_unity_projects_matchthemall_copy_assets_match_them_all_scripts_gameplay_itemspotmanager_cs", "target": "zlinq", "relation": "imports", "context": "import", "confidence": "EXTRACTED", "source_file": "Gameplay/ItemSpotManager.cs", "source_location": "L3", "weight": 1.0}, {"source": "e_unity_projects_matchthemall_copy_assets_match_them_all_scripts_gameplay_itemspotmanager_cs", "target": "unityengine", "relation": "imports", "context": "import", "confidence": "EXTRACTED", "source_file": "Gameplay/ItemSpotManager.cs", "source_location": "L4", "weight": 1.0}, {"source": "e_unity_projects_matchthemall_copy_assets_match_them_all_scripts_gameplay_itemspotmanager_cs", "target": "primetween", "relation": "imports", "context": "import", "confidence": "EXTRACTED", "source_file": "Gameplay/ItemSpotManager.cs", "source_location": "L5", "weight": 1.0}, {"source": "e_unity_projects_matchthemall_copy_assets_match_them_all_scripts_gameplay_itemspotmanager_cs", "target": "gameplay_itemspotmanager_matchthemall_scripts", "relation": "contains", "confidence": "EXTRACTED", "source_file": "Gameplay/ItemSpotManager.cs", "source_location": "L7", "weight": 1.0}, {"source": "e_unity_projects_matchthemall_copy_assets_match_them_all_scripts_gameplay_itemspotmanager_cs", "target": "gameplay_itemspotmanager_itemspotmanager", "relation": "contains", "confidence": "EXTRACTED", "source_file": "Gameplay/ItemSpotManager.cs", "source_location": "L9", "weight": 1.0}, {"source": "gameplay_itemspotmanager_itemspotmanager", "target": "monobehaviour", "relation": "inherits", "confidence": "EXTRACTED", "source_file": "Gameplay/ItemSpotManager.cs", "source_location": "L9", "weight": 1.0}, {"source": "gameplay_itemspotmanager_itemspotmanager", "target": "transform", "relation": "references", "confidence": "EXTRACTED", "source_file": "Gameplay/ItemSpotManager.cs", "source_location": "L13", "weight": 1.0, "context": "field"}, {"source": "gameplay_itemspotmanager_itemspotmanager", "target": "itemspot", "relation": "references", "confidence": "EXTRACTED", "source_file": "Gameplay/ItemSpotManager.cs", "source_location": "L15", "weight": 1.0, "context": "field"}, {"source": "gameplay_itemspotmanager_itemspotmanager", "target": "int", "relation": "references", "confidence": "EXTRACTED", "source_file": "Gameplay/ItemSpotManager.cs", "source_location": "L16", "weight": 1.0, "context": "field"}, {"source": "gameplay_itemspotmanager_itemspotmanager", "target": "vector3", "relation": "references", "confidence": "EXTRACTED", "source_file": "Gameplay/ItemSpotManager.cs", "source_location": "L18", "weight": 1.0, "context": "field"}, {"source": "gameplay_itemspotmanager_itemspotmanager", "target": "vector3", "relation": "references", "confidence": "EXTRACTED", "source_file": "Gameplay/ItemSpotManager.cs", "source_location": "L20", "weight": 1.0, "context": "field"}, {"source": "gameplay_itemspotmanager_itemspotmanager", "target": "float", "relation": "references", "confidence": "EXTRACTED", "source_file": "Gameplay/ItemSpotManager.cs", "source_location": "L22", "weight": 1.0, "context": "field"}, {"source": "gameplay_itemspotmanager_itemspotmanager", "target": "ease", "relation": "references", "confidence": "EXTRACTED", "source_file": "Gameplay/ItemSpotManager.cs", "source_location": "L24", "weight": 1.0, "context": "field"}, {"source": "gameplay_itemspotmanager_itemspotmanager", "target": "action", "relation": "references", "confidence": "EXTRACTED", "source_file": "Gameplay/ItemSpotManager.cs", "source_location": "L26", "weight": 1.0, "context": "field"}, {"source": "gameplay_itemspotmanager_itemspotmanager", "target": "gameplay_itemspotmanager_itemspotmanager_awake", "relation": "method", "confidence": "EXTRACTED", "source_file": "Gameplay/ItemSpotManager.cs", "source_location": "L29", "weight": 1.0}, {"source": "gameplay_itemspotmanager_itemspotmanager", "target": "gameplay_itemspotmanager_itemspotmanager_start", "relation": "method", "confidence": "EXTRACTED", "source_file": "Gameplay/ItemSpotManager.cs", "source_location": "L45", "weight": 1.0}, {"source": "gameplay_itemspotmanager_itemspotmanager", "target": "gameplay_itemspotmanager_itemspotmanager_ondestroy", "relation": "method", "confidence": "EXTRACTED", "source_file": "Gameplay/ItemSpotManager.cs", "source_location": "L51", "weight": 1.0}, {"source": "gameplay_itemspotmanager_itemspotmanager", "target": "gameplay_itemspotmanager_itemspotmanager_onitembacktogame", "relation": "method", "confidence": "EXTRACTED", "source_file": "Gameplay/ItemSpotManager.cs", "source_location": "L59", "weight": 1.0}, {"source": "gameplay_itemspotmanager_itemspotmanager_onitembacktogame", "target": "item", "relation": "references", "confidence": "EXTRACTED", "source_file": "Gameplay/ItemSpotManager.cs", "source_location": "L59", "weight": 1.0, "context": "parameter_type"}, {"source": "gameplay_itemspotmanager_itemspotmanager", "target": "gameplay_itemspotmanager_itemspotmanager_onlevelspawned", "relation": "method", "confidence": "EXTRACTED", "source_file": "Gameplay/ItemSpotManager.cs", "source_location": "L66", "weight": 1.0}, {"source": "gameplay_itemspotmanager_itemspotmanager_onlevelspawned", "target": "level", "relation": "references", "confidence": "EXTRACTED", "source_file": "Gameplay/ItemSpotManager.cs", "source_location": "L66", "weight": 1.0, "context": "parameter_type"}, {"source": "gameplay_itemspotmanager_itemspotmanager", "target": "gameplay_itemspotmanager_itemspotmanager_resetspotsandstate", "relation": "method", "confidence": "EXTRACTED", "source_file": "Gameplay/ItemSpotManager.cs", "source_location": "L83", "weight": 1.0}, {"source": "gameplay_itemspotmanager_itemspotmanager", "target": "gameplay_itemspotmanager_itemspotmanager_onitemclickedevent", "relation": "method", "confidence": "EXTRACTED", "source_file": "Gameplay/ItemSpotManager.cs", "source_location": "L102", "weight": 1.0}, {"source": "gameplay_itemspotmanager_itemspotmanager_onitemclickedevent", "target": "itemclickedevent", "relation": "references", "confidence": "EXTRACTED", "source_file": "Gameplay/ItemSpotManager.cs", "source_location": "L102", "weight": 1.0, "context": "parameter_type"}, {"source": "gameplay_itemspotmanager_itemspotmanager", "target": "gameplay_itemspotmanager_itemspotmanager_handleitemclick", "relation": "method", "confidence": "EXTRACTED", "source_file": "Gameplay/ItemSpotManager.cs", "source_location": "L116", "weight": 1.0}, {"source": "gameplay_itemspotmanager_itemspotmanager_handleitemclick", "target": "item", "relation": "references", "confidence": "EXTRACTED", "source_file": "Gameplay/ItemSpotManager.cs", "source_location": "L116", "weight": 1.0, "context": "parameter_type"}, {"source": "gameplay_itemspotmanager_itemspotmanager", "target": "gameplay_itemspotmanager_itemspotmanager_getidealspotfor", "relation": "method", "confidence": "EXTRACTED", "source_file": "Gameplay/ItemSpotManager.cs", "source_location": "L126", "weight": 1.0}, {"source": "gameplay_itemspotmanager_itemspotmanager_getidealspotfor", "target": "item", "relation": "references", "confidence": "EXTRACTED", "source_file": "Gameplay/ItemSpotManager.cs", "source_location": "L126", "weight": 1.0, "context": "parameter_type"}, {"source": "gameplay_itemspotmanager_itemspotmanager_getidealspotfor", "target": "itemspot", "relation": "references", "confidence": "EXTRACTED", "source_file": "Gameplay/ItemSpotManager.cs", "source_location": "L126", "weight": 1.0, "context": "return_type"}, {"source": "gameplay_itemspotmanager_itemspotmanager", "target": "gameplay_itemspotmanager_itemspotmanager_trymoveitemtoidealspot", "relation": "method", "confidence": "EXTRACTED", "source_file": "Gameplay/ItemSpotManager.cs", "source_location": "L138", "weight": 1.0}, {"source": "gameplay_itemspotmanager_itemspotmanager_trymoveitemtoidealspot", "target": "item", "relation": "references", "confidence": "EXTRACTED", "source_file": "Gameplay/ItemSpotManager.cs", "source_location": "L138", "weight": 1.0, "context": "parameter_type"}, {"source": "gameplay_itemspotmanager_itemspotmanager_trymoveitemtoidealspot", "target": "itemspot", "relation": "references", "confidence": "EXTRACTED", "source_file": "Gameplay/ItemSpotManager.cs", "source_location": "L138", "weight": 1.0, "context": "parameter_type"}, {"source": "gameplay_itemspotmanager_itemspotmanager", "target": "gameplay_itemspotmanager_itemspotmanager_moveitemtospot", "relation": "method", "confidence": "EXTRACTED", "source_file": "Gameplay/ItemSpotManager.cs", "source_location": "L149", "weight": 1.0}, {"source": "gameplay_itemspotmanager_itemspotmanager_moveitemtospot", "target": "item", "relation": "references", "confidence": "EXTRACTED", "source_file": "Gameplay/ItemSpotManager.cs", "source_location": "L149", "weight": 1.0, "context": "parameter_type"}, {"source": "gameplay_itemspotmanager_itemspotmanager_moveitemtospot", "target": "itemspot", "relation": "references", "confidence": "EXTRACTED", "source_file": "Gameplay/ItemSpotManager.cs", "source_location": "L149", "weight": 1.0, "context": "parameter_type"}, {"source": "gameplay_itemspotmanager_itemspotmanager_moveitemtospot", "target": "action", "relation": "references", "confidence": "EXTRACTED", "source_file": "Gameplay/ItemSpotManager.cs", "source_location": "L149", "weight": 1.0, "context": "parameter_type"}, {"source": "gameplay_itemspotmanager_itemspotmanager", "target": "gameplay_itemspotmanager_itemspotmanager_handleitemreachedspot", "relation": "method", "confidence": "EXTRACTED", "source_file": "Gameplay/ItemSpotManager.cs", "source_location": "L166", "weight": 1.0}, {"source": "gameplay_itemspotmanager_itemspotmanager_handleitemreachedspot", "target": "item", "relation": "references", "confidence": "EXTRACTED", "source_file": "Gameplay/ItemSpotManager.cs", "source_location": "L166", "weight": 1.0, "context": "parameter_type"}, {"source": "gameplay_itemspotmanager_itemspotmanager", "target": "gameplay_itemspotmanager_itemspotmanager_onmergestarted", "relation": "method", "confidence": "EXTRACTED", "source_file": "Gameplay/ItemSpotManager.cs", "source_location": "L176", "weight": 1.0}, {"source": "gameplay_itemspotmanager_itemspotmanager_onmergestarted", "target": "mergestartedevent", "relation": "references", "confidence": "EXTRACTED", "source_file": "Gameplay/ItemSpotManager.cs", "source_location": "L176", "weight": 1.0, "context": "parameter_type"}, {"source": "gameplay_itemspotmanager_itemspotmanager", "target": "gameplay_itemspotmanager_itemspotmanager_moveallitemstotheleft", "relation": "method", "confidence": "EXTRACTED", "source_file": "Gameplay/ItemSpotManager.cs", "source_location": "L184", "weight": 1.0}, {"source": "gameplay_itemspotmanager_itemspotmanager", "target": "gameplay_itemspotmanager_itemspotmanager_moveallitemstotherightfrom", "relation": "method", "confidence": "EXTRACTED", "source_file": "Gameplay/ItemSpotManager.cs", "source_location": "L210", "weight": 1.0}, {"source": "gameplay_itemspotmanager_itemspotmanager_moveallitemstotherightfrom", "target": "itemspot", "relation": "references", "confidence": "EXTRACTED", "source_file": "Gameplay/ItemSpotManager.cs", "source_location": "L210", "weight": 1.0, "context": "parameter_type"}, {"source": "gameplay_itemspotmanager_itemspotmanager_moveallitemstotherightfrom", "target": "item", "relation": "references", "confidence": "EXTRACTED", "source_file": "Gameplay/ItemSpotManager.cs", "source_location": "L210", "weight": 1.0, "context": "parameter_type"}, {"source": "gameplay_itemspotmanager_itemspotmanager", "target": "gameplay_itemspotmanager_itemspotmanager_moveitemtofirstfreespot", "relation": "method", "confidence": "EXTRACTED", "source_file": "Gameplay/ItemSpotManager.cs", "source_location": "L264", "weight": 1.0}, {"source": "gameplay_itemspotmanager_itemspotmanager_moveitemtofirstfreespot", "target": "item", "relation": "references", "confidence": "EXTRACTED", "source_file": "Gameplay/ItemSpotManager.cs", "source_location": "L264", "weight": 1.0, "context": "parameter_type"}, {"source": "gameplay_itemspotmanager_itemspotmanager", "target": "gameplay_itemspotmanager_itemspotmanager_getfreespot", "relation": "method", "confidence": "EXTRACTED", "source_file": "Gameplay/ItemSpotManager.cs", "source_location": "L279", "weight": 1.0}, {"source": "gameplay_itemspotmanager_itemspotmanager_getfreespot", "target": "itemspot", "relation": "references", "confidence": "EXTRACTED", "source_file": "Gameplay/ItemSpotManager.cs", "source_location": "L279", "weight": 1.0, "context": "return_type"}, {"source": "gameplay_itemspotmanager_itemspotmanager", "target": "gameplay_itemspotmanager_itemspotmanager_isfreespotavailable", "relation": "method", "confidence": "EXTRACTED", "source_file": "Gameplay/ItemSpotManager.cs", "source_location": "L281", "weight": 1.0}, {"source": "gameplay_itemspotmanager_itemspotmanager", "target": "gameplay_itemspotmanager_itemspotmanager_storespot", "relation": "method", "confidence": "EXTRACTED", "source_file": "Gameplay/ItemSpotManager.cs", "source_location": "L283", "weight": 1.0}, {"source": "gameplay_itemspotmanager_itemspotmanager", "target": "gameplay_itemspotmanager_itemspotmanager_getrandomoccupiedspot", "relation": "method", "confidence": "EXTRACTED", "source_file": "Gameplay/ItemSpotManager.cs", "source_location": "L290", "weight": 1.0}, {"source": "gameplay_itemspotmanager_itemspotmanager_getrandomoccupiedspot", "target": "itemspot", "relation": "references", "confidence": "EXTRACTED", "source_file": "Gameplay/ItemSpotManager.cs", "source_location": "L290", "weight": 1.0, "context": "return_type"}, {"source": "gameplay_itemspotmanager_itemspotmanager", "target": "gameplay_itemspotmanager_itemspotmanager_hasitemonboard", "relation": "method", "confidence": "EXTRACTED", "source_file": "Gameplay/ItemSpotManager.cs", "source_location": "L299", "weight": 1.0}, {"source": "gameplay_itemspotmanager_itemspotmanager_hasitemonboard", "target": "eitemname", "relation": "references", "confidence": "EXTRACTED", "source_file": "Gameplay/ItemSpotManager.cs", "source_location": "L299", "weight": 1.0, "context": "parameter_type"}, {"source": "gameplay_itemspotmanager_itemspotmanager", "target": "gameplay_itemspotmanager_itemspotmanager_getitemsonboard", "relation": "method", "confidence": "EXTRACTED", "source_file": "Gameplay/ItemSpotManager.cs", "source_location": "L309", "weight": 1.0}, {"source": "gameplay_itemspotmanager_itemspotmanager_getitemsonboard", "target": "eitemname", "relation": "references", "confidence": "EXTRACTED", "source_file": "Gameplay/ItemSpotManager.cs", "source_location": "L309", "weight": 1.0, "context": "parameter_type"}, {"source": "gameplay_itemspotmanager_itemspotmanager_getitemsonboard", "target": "list", "relation": "references", "confidence": "EXTRACTED", "source_file": "Gameplay/ItemSpotManager.cs", "source_location": "L309", "weight": 1.0, "context": "return_type"}, {"source": "gameplay_itemspotmanager_itemspotmanager_getitemsonboard", "target": "item", "relation": "references", "confidence": "EXTRACTED", "source_file": "Gameplay/ItemSpotManager.cs", "source_location": "L309", "weight": 1.0, "context": "generic_arg"}, {"source": "gameplay_itemspotmanager_itemspotmanager", "target": "gameplay_itemspotmanager_itemspotmanager_getoccupieditemtypes", "relation": "method", "confidence": "EXTRACTED", "source_file": "Gameplay/ItemSpotManager.cs", "source_location": "L320", "weight": 1.0}, {"source": "gameplay_itemspotmanager_itemspotmanager_getoccupieditemtypes", "target": "ienumerable", "relation": "references", "confidence": "EXTRACTED", "source_file": "Gameplay/ItemSpotManager.cs", "source_location": "L320", "weight": 1.0, "context": "return_type"}, {"source": "gameplay_itemspotmanager_itemspotmanager_getoccupieditemtypes", "target": "eitemname", "relation": "references", "confidence": "EXTRACTED", "source_file": "Gameplay/ItemSpotManager.cs", "source_location": "L320", "weight": 1.0, "context": "generic_arg"}, {"source": "gameplay_itemspotmanager_itemspotmanager", "target": "gameplay_itemspotmanager_itemspotmanager_isboardfullandnoitemsmoving", "relation": "method", "confidence": "EXTRACTED", "source_file": "Gameplay/ItemSpotManager.cs", "source_location": "L331", "weight": 1.0}, {"source": "gameplay_itemspotmanager_itemspotmanager", "target": "gameplay_itemspotmanager_itemspotmanager_getbesthintitems", "relation": "method", "confidence": "EXTRACTED", "source_file": "Gameplay/ItemSpotManager.cs", "source_location": "L341", "weight": 1.0}, {"source": "gameplay_itemspotmanager_itemspotmanager_getbesthintitems", "target": "list", "relation": "references", "confidence": "EXTRACTED", "source_file": "Gameplay/ItemSpotManager.cs", "source_location": "L341", "weight": 1.0, "context": "return_type"}, {"source": "gameplay_itemspotmanager_itemspotmanager_getbesthintitems", "target": "item", "relation": "references", "confidence": "EXTRACTED", "source_file": "Gameplay/ItemSpotManager.cs", "source_location": "L341", "weight": 1.0, "context": "generic_arg"}, {"source": "gameplay_itemspotmanager_itemspotmanager_awake", "target": "gameplay_itemspotmanager_itemspotmanager_storespot", "relation": "calls", "context": "call", "confidence": "EXTRACTED", "source_file": "Gameplay/ItemSpotManager.cs", "source_location": "L42", "weight": 1.0}, {"source": "gameplay_itemspotmanager_itemspotmanager_onitembacktogame", "target": "gameplay_itemspotmanager_itemspotmanager_moveallitemstotheleft", "relation": "calls", "context": "call", "confidence": "EXTRACTED", "source_file": "Gameplay/ItemSpotManager.cs", "source_location": "L63", "weight": 1.0}, {"source": "gameplay_itemspotmanager_itemspotmanager_onlevelspawned", "target": "gameplay_itemspotmanager_itemspotmanager_resetspotsandstate", "relation": "calls", "context": "call", "confidence": "EXTRACTED", "source_file": "Gameplay/ItemSpotManager.cs", "source_location": "L80", "weight": 1.0}, {"source": "gameplay_itemspotmanager_itemspotmanager_onitemclickedevent", "target": "gameplay_itemspotmanager_itemspotmanager_isfreespotavailable", "relation": "calls", "context": "call", "confidence": "EXTRACTED", "source_file": "Gameplay/ItemSpotManager.cs", "source_location": "L106", "weight": 1.0}, {"source": "gameplay_itemspotmanager_itemspotmanager_onitemclickedevent", "target": "gameplay_itemspotmanager_itemspotmanager_handleitemclick", "relation": "calls", "context": "call", "confidence": "EXTRACTED", "source_file": "Gameplay/ItemSpotManager.cs", "source_location": "L113", "weight": 1.0}, {"source": "gameplay_itemspotmanager_itemspotmanager_handleitemclick", "target": "gameplay_itemspotmanager_itemspotmanager_hasitemonboard", "relation": "calls", "context": "call", "confidence": "EXTRACTED", "source_file": "Gameplay/ItemSpotManager.cs", "source_location": "L118", "weight": 1.0}, {"source": "gameplay_itemspotmanager_itemspotmanager_handleitemclick", "target": "gameplay_itemspotmanager_itemspotmanager_getidealspotfor", "relation": "calls", "context": "call", "confidence": "EXTRACTED", "source_file": "Gameplay/ItemSpotManager.cs", "source_location": "L120", "weight": 1.0}, {"source": "gameplay_itemspotmanager_itemspotmanager_handleitemclick", "target": "gameplay_itemspotmanager_itemspotmanager_trymoveitemtoidealspot", "relation": "calls", "context": "call", "confidence": "EXTRACTED", "source_file": "Gameplay/ItemSpotManager.cs", "source_location": "L121", "weight": 1.0}, {"source": "gameplay_itemspotmanager_itemspotmanager_handleitemclick", "target": "gameplay_itemspotmanager_itemspotmanager_moveitemtofirstfreespot", "relation": "calls", "context": "call", "confidence": "EXTRACTED", "source_file": "Gameplay/ItemSpotManager.cs", "source_location": "L123", "weight": 1.0}, {"source": "gameplay_itemspotmanager_itemspotmanager_trymoveitemtoidealspot", "target": "gameplay_itemspotmanager_itemspotmanager_moveallitemstotherightfrom", "relation": "calls", "context": "call", "confidence": "EXTRACTED", "source_file": "Gameplay/ItemSpotManager.cs", "source_location": "L142", "weight": 1.0}, {"source": "gameplay_itemspotmanager_itemspotmanager_trymoveitemtoidealspot", "target": "gameplay_itemspotmanager_itemspotmanager_moveitemtospot", "relation": "calls", "context": "call", "confidence": "EXTRACTED", "source_file": "Gameplay/ItemSpotManager.cs", "source_location": "L146", "weight": 1.0}, {"source": "gameplay_itemspotmanager_itemspotmanager_trymoveitemtoidealspot", "target": "gameplay_itemspotmanager_itemspotmanager_handleitemreachedspot", "relation": "calls", "context": "call", "confidence": "EXTRACTED", "source_file": "Gameplay/ItemSpotManager.cs", "source_location": "L146", "weight": 1.0}, {"source": "gameplay_itemspotmanager_itemspotmanager_onmergestarted", "target": "gameplay_itemspotmanager_itemspotmanager_moveallitemstotheleft", "relation": "calls", "context": "call", "confidence": "EXTRACTED", "source_file": "Gameplay/ItemSpotManager.cs", "source_location": "L181", "weight": 1.0}, {"source": "gameplay_itemspotmanager_itemspotmanager_moveallitemstotheleft", "target": "gameplay_itemspotmanager_itemspotmanager_moveitemtospot", "relation": "calls", "context": "call", "confidence": "EXTRACTED", "source_file": "Gameplay/ItemSpotManager.cs", "source_location": "L203", "weight": 1.0}, {"source": "gameplay_itemspotmanager_itemspotmanager_moveallitemstotheleft", "target": "gameplay_itemspotmanager_itemspotmanager_handleitemreachedspot", "relation": "calls", "context": "call", "confidence": "EXTRACTED", "source_file": "Gameplay/ItemSpotManager.cs", "source_location": "L203", "weight": 1.0}, {"source": "gameplay_itemspotmanager_itemspotmanager_moveallitemstotherightfrom", "target": "gameplay_itemspotmanager_itemspotmanager_moveitemtospot", "relation": "calls", "context": "call", "confidence": "EXTRACTED", "source_file": "Gameplay/ItemSpotManager.cs", "source_location": "L253", "weight": 1.0}, {"source": "gameplay_itemspotmanager_itemspotmanager_moveallitemstotherightfrom", "target": "gameplay_itemspotmanager_itemspotmanager_handleitemreachedspot", "relation": "calls", "context": "call", "confidence": "EXTRACTED", "source_file": "Gameplay/ItemSpotManager.cs", "source_location": "L253", "weight": 1.0}, {"source": "gameplay_itemspotmanager_itemspotmanager_moveitemtofirstfreespot", "target": "gameplay_itemspotmanager_itemspotmanager_getfreespot", "relation": "calls", "context": "call", "confidence": "EXTRACTED", "source_file": "Gameplay/ItemSpotManager.cs", "source_location": "L266", "weight": 1.0}, {"source": "gameplay_itemspotmanager_itemspotmanager_moveitemtofirstfreespot", "target": "gameplay_itemspotmanager_itemspotmanager_moveitemtospot", "relation": "calls", "context": "call", "confidence": "EXTRACTED", "source_file": "Gameplay/ItemSpotManager.cs", "source_location": "L274", "weight": 1.0}, {"source": "gameplay_itemspotmanager_itemspotmanager_moveitemtofirstfreespot", "target": "gameplay_itemspotmanager_itemspotmanager_handleitemreachedspot", "relation": "calls", "context": "call", "confidence": "EXTRACTED", "source_file": "Gameplay/ItemSpotManager.cs", "source_location": "L274", "weight": 1.0}, {"source": "gameplay_itemspotmanager_itemspotmanager_isfreespotavailable", "target": "gameplay_itemspotmanager_itemspotmanager_getfreespot", "relation": "calls", "context": "call", "confidence": "EXTRACTED", "source_file": "Gameplay/ItemSpotManager.cs", "source_location": "L281", "weight": 1.0}, {"source": "gameplay_itemspotmanager_itemspotmanager_isboardfullandnoitemsmoving", "target": "gameplay_itemspotmanager_itemspotmanager_getfreespot", "relation": "calls", "context": "call", "confidence": "EXTRACTED", "source_file": "Gameplay/ItemSpotManager.cs", "source_location": "L333", "weight": 1.0}, {"source": "gameplay_itemspotmanager_itemspotmanager_getbesthintitems", "target": "gameplay_itemspotmanager_itemspotmanager_getoccupieditemtypes", "relation": "calls", "context": "call", "confidence": "EXTRACTED", "source_file": "Gameplay/ItemSpotManager.cs", "source_location": "L347", "weight": 1.0}], "raw_calls": [{"caller_nid": "gameplay_itemspotmanager_itemspotmanager_awake", "callee": "Destroy", "is_member_call": false, "source_file": "E:\\Unity Projects\\MatchThemAll - Copy\\Assets\\Match Them All\\Scripts\\Gameplay\\ItemSpotManager.cs", "source_location": "L33", "receiver": null}, {"caller_nid": "gameplay_itemspotmanager_itemspotmanager_awake", "callee": "GetComponent<MatchSystem>", "is_member_call": true, "source_file": "E:\\Unity Projects\\MatchThemAll - Copy\\Assets\\Match Them All\\Scripts\\Gameplay\\ItemSpotManager.cs", "source_location": "L35", "receiver": null}, {"caller_nid": "gameplay_itemspotmanager_itemspotmanager_awake", "callee": "AddComponent<MatchSystem>", "is_member_call": true, "source_file": "E:\\Unity Projects\\MatchThemAll - Copy\\Assets\\Match Them All\\Scripts\\Gameplay\\ItemSpotManager.cs", "source_location": "L36", "receiver": null}, {"caller_nid": "gameplay_itemspotmanager_itemspotmanager_awake", "callee": "Subscribe<ItemClickedEvent>", "is_member_call": true, "source_file": "E:\\Unity Projects\\MatchThemAll - Copy\\Assets\\Match Them All\\Scripts\\Gameplay\\ItemSpotManager.cs", "source_location": "L38", "receiver": null}, {"caller_nid": "gameplay_itemspotmanager_itemspotmanager_awake", "callee": "Subscribe<MergeStartedEvent>", "is_member_call": true, "source_file": "E:\\Unity Projects\\MatchThemAll - Copy\\Assets\\Match Them All\\Scripts\\Gameplay\\ItemSpotManager.cs", "source_location": "L39", "receiver": null}, {"caller_nid": "gameplay_itemspotmanager_itemspotmanager_ondestroy", "callee": "Unsubscribe<ItemClickedEvent>", "is_member_call": true, "source_file": "E:\\Unity Projects\\MatchThemAll - Copy\\Assets\\Match Them All\\Scripts\\Gameplay\\ItemSpotManager.cs", "source_location": "L53", "receiver": null}, {"caller_nid": "gameplay_itemspotmanager_itemspotmanager_ondestroy", "callee": "Unsubscribe<MergeStartedEvent>", "is_member_call": true, "source_file": "E:\\Unity Projects\\MatchThemAll - Copy\\Assets\\Match Them All\\Scripts\\Gameplay\\ItemSpotManager.cs", "source_location": "L54", "receiver": null}, {"caller_nid": "gameplay_itemspotmanager_itemspotmanager_onitembacktogame", "callee": "Clear", "is_member_call": true, "source_file": "E:\\Unity Projects\\MatchThemAll - Copy\\Assets\\Match Them All\\Scripts\\Gameplay\\ItemSpotManager.cs", "source_location": "L62", "receiver": null}, {"caller_nid": "gameplay_itemspotmanager_itemspotmanager_onlevelspawned", "callee": "SetActive", "is_member_call": true, "source_file": "E:\\Unity Projects\\MatchThemAll - Copy\\Assets\\Match Them All\\Scripts\\Gameplay\\ItemSpotManager.cs", "source_location": "L74", "receiver": null}, {"caller_nid": "gameplay_itemspotmanager_itemspotmanager_onlevelspawned", "callee": "TryGetComponent<ItemSpotLayout>", "is_member_call": true, "source_file": "E:\\Unity Projects\\MatchThemAll - Copy\\Assets\\Match Them All\\Scripts\\Gameplay\\ItemSpotManager.cs", "source_location": "L77", "receiver": null}, {"caller_nid": "gameplay_itemspotmanager_itemspotmanager_onlevelspawned", "callee": "UpdateLayout", "is_member_call": true, "source_file": "E:\\Unity Projects\\MatchThemAll - Copy\\Assets\\Match Them All\\Scripts\\Gameplay\\ItemSpotManager.cs", "source_location": "L78", "receiver": null}, {"caller_nid": "gameplay_itemspotmanager_itemspotmanager_resetspotsandstate", "callee": "StopAll", "is_member_call": true, "source_file": "E:\\Unity Projects\\MatchThemAll - Copy\\Assets\\Match Them All\\Scripts\\Gameplay\\ItemSpotManager.cs", "source_location": "L93", "receiver": null}, {"caller_nid": "gameplay_itemspotmanager_itemspotmanager_resetspotsandstate", "callee": "ReleaseItem", "is_member_call": true, "source_file": "E:\\Unity Projects\\MatchThemAll - Copy\\Assets\\Match Them All\\Scripts\\Gameplay\\ItemSpotManager.cs", "source_location": "L94", "receiver": null}, {"caller_nid": "gameplay_itemspotmanager_itemspotmanager_resetspotsandstate", "callee": "Clear", "is_member_call": true, "source_file": "E:\\Unity Projects\\MatchThemAll - Copy\\Assets\\Match Them All\\Scripts\\Gameplay\\ItemSpotManager.cs", "source_location": "L96", "receiver": null}, {"caller_nid": "gameplay_itemspotmanager_itemspotmanager_onitemclickedevent", "callee": "Log", "is_member_call": true, "source_file": "E:\\Unity Projects\\MatchThemAll - Copy\\Assets\\Match Them All\\Scripts\\Gameplay\\ItemSpotManager.cs", "source_location": "L108", "receiver": null}, {"caller_nid": "gameplay_itemspotmanager_itemspotmanager_onitemclickedevent", "callee": "Invoke", "is_member_call": true, "source_file": "E:\\Unity Projects\\MatchThemAll - Copy\\Assets\\Match Them All\\Scripts\\Gameplay\\ItemSpotManager.cs", "source_location": "L112", "receiver": null}, {"caller_nid": "gameplay_itemspotmanager_itemspotmanager_getidealspotfor", "callee": "IsEmpty", "is_member_call": true, "source_file": "E:\\Unity Projects\\MatchThemAll - Copy\\Assets\\Match Them All\\Scripts\\Gameplay\\ItemSpotManager.cs", "source_location": "L131", "receiver": null}, {"caller_nid": "gameplay_itemspotmanager_itemspotmanager_getidealspotfor", "callee": "Clamp", "is_member_call": true, "source_file": "E:\\Unity Projects\\MatchThemAll - Copy\\Assets\\Match Them All\\Scripts\\Gameplay\\ItemSpotManager.cs", "source_location": "L134", "receiver": null}, {"caller_nid": "gameplay_itemspotmanager_itemspotmanager_trymoveitemtoidealspot", "callee": "IsEmpty", "is_member_call": true, "source_file": "E:\\Unity Projects\\MatchThemAll - Copy\\Assets\\Match Them All\\Scripts\\Gameplay\\ItemSpotManager.cs", "source_location": "L140", "receiver": null}, {"caller_nid": "gameplay_itemspotmanager_itemspotmanager_moveitemtospot", "callee": "Populate", "is_member_call": true, "source_file": "E:\\Unity Projects\\MatchThemAll - Copy\\Assets\\Match Them All\\Scripts\\Gameplay\\ItemSpotManager.cs", "source_location": "L152", "receiver": null}, {"caller_nid": "gameplay_itemspotmanager_itemspotmanager_moveitemtospot", "callee": "StopAll", "is_member_call": true, "source_file": "E:\\Unity Projects\\MatchThemAll - Copy\\Assets\\Match Them All\\Scripts\\Gameplay\\ItemSpotManager.cs", "source_location": "L155", "receiver": null}, {"caller_nid": "gameplay_itemspotmanager_itemspotmanager_moveitemtospot", "callee": "LocalPosition", "is_member_call": true, "source_file": "E:\\Unity Projects\\MatchThemAll - Copy\\Assets\\Match Them All\\Scripts\\Gameplay\\ItemSpotManager.cs", "source_location": "L157", "receiver": null}, {"caller_nid": "gameplay_itemspotmanager_itemspotmanager_moveitemtospot", "callee": "Scale", "is_member_call": true, "source_file": "E:\\Unity Projects\\MatchThemAll - Copy\\Assets\\Match Them All\\Scripts\\Gameplay\\ItemSpotManager.cs", "source_location": "L158", "receiver": null}, {"caller_nid": "gameplay_itemspotmanager_itemspotmanager_moveitemtospot", "callee": "OnComplete", "is_member_call": true, "source_file": "E:\\Unity Projects\\MatchThemAll - Copy\\Assets\\Match Them All\\Scripts\\Gameplay\\ItemSpotManager.cs", "source_location": "L159", "receiver": null}, {"caller_nid": "gameplay_itemspotmanager_itemspotmanager_moveitemtospot", "callee": "LocalRotation", "is_member_call": true, "source_file": "E:\\Unity Projects\\MatchThemAll - Copy\\Assets\\Match Them All\\Scripts\\Gameplay\\ItemSpotManager.cs", "source_location": "L159", "receiver": null}, {"caller_nid": "gameplay_itemspotmanager_itemspotmanager_moveitemtospot", "callee": "DisableShadow", "is_member_call": true, "source_file": "E:\\Unity Projects\\MatchThemAll - Copy\\Assets\\Match Them All\\Scripts\\Gameplay\\ItemSpotManager.cs", "source_location": "L162", "receiver": null}, {"caller_nid": "gameplay_itemspotmanager_itemspotmanager_moveitemtospot", "callee": "DisablePhysics", "is_member_call": true, "source_file": "E:\\Unity Projects\\MatchThemAll - Copy\\Assets\\Match Them All\\Scripts\\Gameplay\\ItemSpotManager.cs", "source_location": "L163", "receiver": null}, {"caller_nid": "gameplay_itemspotmanager_itemspotmanager_handleitemreachedspot", "callee": "BumpDown", "is_member_call": true, "source_file": "E:\\Unity Projects\\MatchThemAll - Copy\\Assets\\Match Them All\\Scripts\\Gameplay\\ItemSpotManager.cs", "source_location": "L169", "receiver": null}, {"caller_nid": "gameplay_itemspotmanager_itemspotmanager_handleitemreachedspot", "callee": "Publish", "is_member_call": true, "source_file": "E:\\Unity Projects\\MatchThemAll - Copy\\Assets\\Match Them All\\Scripts\\Gameplay\\ItemSpotManager.cs", "source_location": "L173", "receiver": null}, {"caller_nid": "gameplay_itemspotmanager_itemspotmanager_onmergestarted", "callee": "Clear", "is_member_call": true, "source_file": "E:\\Unity Projects\\MatchThemAll - Copy\\Assets\\Match Them All\\Scripts\\Gameplay\\ItemSpotManager.cs", "source_location": "L179", "receiver": null}, {"caller_nid": "gameplay_itemspotmanager_itemspotmanager_moveallitemstotheleft", "callee": "IsEmpty", "is_member_call": true, "source_file": "E:\\Unity Projects\\MatchThemAll - Copy\\Assets\\Match Them All\\Scripts\\Gameplay\\ItemSpotManager.cs", "source_location": "L193", "receiver": null}, {"caller_nid": "gameplay_itemspotmanager_itemspotmanager_moveallitemstotheleft", "callee": "Clear", "is_member_call": true, "source_file": "E:\\Unity Projects\\MatchThemAll - Copy\\Assets\\Match Them All\\Scripts\\Gameplay\\ItemSpotManager.cs", "source_location": "L202", "receiver": null}, {"caller_nid": "gameplay_itemspotmanager_itemspotmanager_moveallitemstotherightfrom", "callee": "GetSiblingIndex", "is_member_call": true, "source_file": "E:\\Unity Projects\\MatchThemAll - Copy\\Assets\\Match Them All\\Scripts\\Gameplay\\ItemSpotManager.cs", "source_location": "L212", "receiver": null}, {"caller_nid": "gameplay_itemspotmanager_itemspotmanager_moveallitemstotherightfrom", "callee": "IsEmpty", "is_member_call": true, "source_file": "E:\\Unity Projects\\MatchThemAll - Copy\\Assets\\Match Them All\\Scripts\\Gameplay\\ItemSpotManager.cs", "source_location": "L217", "receiver": null}, {"caller_nid": "gameplay_itemspotmanager_itemspotmanager_moveallitemstotherightfrom", "callee": "IsEmpty", "is_member_call": true, "source_file": "E:\\Unity Projects\\MatchThemAll - Copy\\Assets\\Match Them All\\Scripts\\Gameplay\\ItemSpotManager.cs", "source_location": "L228", "receiver": null}, {"caller_nid": "gameplay_itemspotmanager_itemspotmanager_moveallitemstotherightfrom", "callee": "LogError", "is_member_call": true, "source_file": "E:\\Unity Projects\\MatchThemAll - Copy\\Assets\\Match Them All\\Scripts\\Gameplay\\ItemSpotManager.cs", "source_location": "L238", "receiver": null}, {"caller_nid": "gameplay_itemspotmanager_itemspotmanager_moveallitemstotherightfrom", "callee": "IsEmpty", "is_member_call": true, "source_file": "E:\\Unity Projects\\MatchThemAll - Copy\\Assets\\Match Them All\\Scripts\\Gameplay\\ItemSpotManager.cs", "source_location": "L247", "receiver": null}, {"caller_nid": "gameplay_itemspotmanager_itemspotmanager_moveallitemstotherightfrom", "callee": "Clear", "is_member_call": true, "source_file": "E:\\Unity Projects\\MatchThemAll - Copy\\Assets\\Match Them All\\Scripts\\Gameplay\\ItemSpotManager.cs", "source_location": "L250", "receiver": null}, {"caller_nid": "gameplay_itemspotmanager_itemspotmanager_moveitemtofirstfreespot", "callee": "Log", "is_member_call": true, "source_file": "E:\\Unity Projects\\MatchThemAll - Copy\\Assets\\Match Them All\\Scripts\\Gameplay\\ItemSpotManager.cs", "source_location": "L270", "receiver": null}, {"caller_nid": "gameplay_itemspotmanager_itemspotmanager_getfreespot", "callee": "FirstOrDefault", "is_member_call": true, "source_file": "E:\\Unity Projects\\MatchThemAll - Copy\\Assets\\Match Them All\\Scripts\\Gameplay\\ItemSpotManager.cs", "source_location": "L279", "receiver": null}, {"caller_nid": "gameplay_itemspotmanager_itemspotmanager_getfreespot", "callee": "Take", "is_member_call": true, "source_file": "E:\\Unity Projects\\MatchThemAll - Copy\\Assets\\Match Them All\\Scripts\\Gameplay\\ItemSpotManager.cs", "source_location": "L279", "receiver": null}, {"caller_nid": "gameplay_itemspotmanager_itemspotmanager_getfreespot", "callee": "AsValueEnumerable", "is_member_call": true, "source_file": "E:\\Unity Projects\\MatchThemAll - Copy\\Assets\\Match Them All\\Scripts\\Gameplay\\ItemSpotManager.cs", "source_location": "L279", "receiver": null}, {"caller_nid": "gameplay_itemspotmanager_itemspotmanager_getfreespot", "callee": "IsEmpty", "is_member_call": true, "source_file": "E:\\Unity Projects\\MatchThemAll - Copy\\Assets\\Match Them All\\Scripts\\Gameplay\\ItemSpotManager.cs", "source_location": "L279", "receiver": null}, {"caller_nid": "gameplay_itemspotmanager_itemspotmanager_storespot", "callee": "GetComponent<ItemSpot>", "is_member_call": true, "source_file": "E:\\Unity Projects\\MatchThemAll - Copy\\Assets\\Match Them All\\Scripts\\Gameplay\\ItemSpotManager.cs", "source_location": "L287", "receiver": null}, {"caller_nid": "gameplay_itemspotmanager_itemspotmanager_storespot", "callee": "GetChild", "is_member_call": true, "source_file": "E:\\Unity Projects\\MatchThemAll - Copy\\Assets\\Match Them All\\Scripts\\Gameplay\\ItemSpotManager.cs", "source_location": "L287", "receiver": null}, {"caller_nid": "gameplay_itemspotmanager_itemspotmanager_getrandomoccupiedspot", "callee": "ToList", "is_member_call": true, "source_file": "E:\\Unity Projects\\MatchThemAll - Copy\\Assets\\Match Them All\\Scripts\\Gameplay\\ItemSpotManager.cs", "source_location": "L292", "receiver": null}, {"caller_nid": "gameplay_itemspotmanager_itemspotmanager_getrandomoccupiedspot", "callee": "Where", "is_member_call": true, "source_file": "E:\\Unity Projects\\MatchThemAll - Copy\\Assets\\Match Them All\\Scripts\\Gameplay\\ItemSpotManager.cs", "source_location": "L292", "receiver": null}, {"caller_nid": "gameplay_itemspotmanager_itemspotmanager_getrandomoccupiedspot", "callee": "Take", "is_member_call": true, "source_file": "E:\\Unity Projects\\MatchThemAll - Copy\\Assets\\Match Them All\\Scripts\\Gameplay\\ItemSpotManager.cs", "source_location": "L292", "receiver": null}, {"caller_nid": "gameplay_itemspotmanager_itemspotmanager_getrandomoccupiedspot", "callee": "AsValueEnumerable", "is_member_call": true, "source_file": "E:\\Unity Projects\\MatchThemAll - Copy\\Assets\\Match Them All\\Scripts\\Gameplay\\ItemSpotManager.cs", "source_location": "L292", "receiver": null}, {"caller_nid": "gameplay_itemspotmanager_itemspotmanager_getrandomoccupiedspot", "callee": "IsEmpty", "is_member_call": true, "source_file": "E:\\Unity Projects\\MatchThemAll - Copy\\Assets\\Match Them All\\Scripts\\Gameplay\\ItemSpotManager.cs", "source_location": "L294", "receiver": null}, {"caller_nid": "gameplay_itemspotmanager_itemspotmanager_getrandomoccupiedspot", "callee": "Range", "is_member_call": true, "source_file": "E:\\Unity Projects\\MatchThemAll - Copy\\Assets\\Match Them All\\Scripts\\Gameplay\\ItemSpotManager.cs", "source_location": "L296", "receiver": null}, {"caller_nid": "gameplay_itemspotmanager_itemspotmanager_hasitemonboard", "callee": "IsEmpty", "is_member_call": true, "source_file": "E:\\Unity Projects\\MatchThemAll - Copy\\Assets\\Match Them All\\Scripts\\Gameplay\\ItemSpotManager.cs", "source_location": "L303", "receiver": null}, {"caller_nid": "gameplay_itemspotmanager_itemspotmanager_getitemsonboard", "callee": "IsEmpty", "is_member_call": true, "source_file": "E:\\Unity Projects\\MatchThemAll - Copy\\Assets\\Match Them All\\Scripts\\Gameplay\\ItemSpotManager.cs", "source_location": "L314", "receiver": null}, {"caller_nid": "gameplay_itemspotmanager_itemspotmanager_getitemsonboard", "callee": "Add", "is_member_call": true, "source_file": "E:\\Unity Projects\\MatchThemAll - Copy\\Assets\\Match Them All\\Scripts\\Gameplay\\ItemSpotManager.cs", "source_location": "L315", "receiver": null}, {"caller_nid": "gameplay_itemspotmanager_itemspotmanager_getoccupieditemtypes", "callee": "IsEmpty", "is_member_call": true, "source_file": "E:\\Unity Projects\\MatchThemAll - Copy\\Assets\\Match Them All\\Scripts\\Gameplay\\ItemSpotManager.cs", "source_location": "L325", "receiver": null}, {"caller_nid": "gameplay_itemspotmanager_itemspotmanager_getoccupieditemtypes", "callee": "Add", "is_member_call": true, "source_file": "E:\\Unity Projects\\MatchThemAll - Copy\\Assets\\Match Them All\\Scripts\\Gameplay\\ItemSpotManager.cs", "source_location": "L326", "receiver": null}, {"caller_nid": "gameplay_itemspotmanager_itemspotmanager_getbesthintitems", "callee": "Any", "is_member_call": true, "source_file": "E:\\Unity Projects\\MatchThemAll - Copy\\Assets\\Match Them All\\Scripts\\Gameplay\\ItemSpotManager.cs", "source_location": "L352", "receiver": null}, {"caller_nid": "gameplay_itemspotmanager_itemspotmanager_getbesthintitems", "callee": "AsValueEnumerable", "is_member_call": true, "source_file": "E:\\Unity Projects\\MatchThemAll - Copy\\Assets\\Match Them All\\Scripts\\Gameplay\\ItemSpotManager.cs", "source_location": "L352", "receiver": null}, {"caller_nid": "gameplay_itemspotmanager_itemspotmanager_getbesthintitems", "callee": "Any", "is_member_call": true, "source_file": "E:\\Unity Projects\\MatchThemAll - Copy\\Assets\\Match Them All\\Scripts\\Gameplay\\ItemSpotManager.cs", "source_location": "L375", "receiver": null}, {"caller_nid": "gameplay_itemspotmanager_itemspotmanager_getbesthintitems", "callee": "AsValueEnumerable", "is_member_call": true, "source_file": "E:\\Unity Projects\\MatchThemAll - Copy\\Assets\\Match Them All\\Scripts\\Gameplay\\ItemSpotManager.cs", "source_location": "L375", "receiver": null}, {"caller_nid": "gameplay_itemspotmanager_itemspotmanager_getbesthintitems", "callee": "FirstOrDefault", "is_member_call": true, "source_file": "E:\\Unity Projects\\MatchThemAll - Copy\\Assets\\Match Them All\\Scripts\\Gameplay\\ItemSpotManager.cs", "source_location": "L393", "receiver": null}, {"caller_nid": "gameplay_itemspotmanager_itemspotmanager_getbesthintitems", "callee": "AsValueEnumerable", "is_member_call": true, "source_file": "E:\\Unity Projects\\MatchThemAll - Copy\\Assets\\Match Them All\\Scripts\\Gameplay\\ItemSpotManager.cs", "source_location": "L393", "receiver": null}, {"caller_nid": "gameplay_itemspotmanager_itemspotmanager_getbesthintitems", "callee": "ToList", "is_member_call": true, "source_file": "E:\\Unity Projects\\MatchThemAll - Copy\\Assets\\Match Them All\\Scripts\\Gameplay\\ItemSpotManager.cs", "source_location": "L403", "receiver": null}, {"caller_nid": "gameplay_itemspotmanager_itemspotmanager_getbesthintitems", "callee": "Where", "is_member_call": true, "source_file": "E:\\Unity Projects\\MatchThemAll - Copy\\Assets\\Match Them All\\Scripts\\Gameplay\\ItemSpotManager.cs", "source_location": "L403", "receiver": null}, {"caller_nid": "gameplay_itemspotmanager_itemspotmanager_getbesthintitems", "callee": "AsValueEnumerable", "is_member_call": true, "source_file": "E:\\Unity Projects\\MatchThemAll - Copy\\Assets\\Match Them All\\Scripts\\Gameplay\\ItemSpotManager.cs", "source_location": "L403", "receiver": null}, {"caller_nid": "gameplay_itemspotmanager_itemspotmanager_getbesthintitems", "callee": "Range", "is_member_call": true, "source_file": "E:\\Unity Projects\\MatchThemAll - Copy\\Assets\\Match Them All\\Scripts\\Gameplay\\ItemSpotManager.cs", "source_location": "L414", "receiver": null}, {"caller_nid": "gameplay_itemspotmanager_itemspotmanager_getbesthintitems", "callee": "Sort", "is_member_call": true, "source_file": "E:\\Unity Projects\\MatchThemAll - Copy\\Assets\\Match Them All\\Scripts\\Gameplay\\ItemSpotManager.cs", "source_location": "L416", "receiver": null}, {"caller_nid": "gameplay_itemspotmanager_itemspotmanager_getbesthintitems", "callee": "CompareTo", "is_member_call": true, "source_file": "E:\\Unity Projects\\MatchThemAll - Copy\\Assets\\Match Them All\\Scripts\\Gameplay\\ItemSpotManager.cs", "source_location": "L417", "receiver": null}, {"caller_nid": "gameplay_itemspotmanager_itemspotmanager_getbesthintitems", "callee": "SqrMagnitude", "is_member_call": true, "source_file": "E:\\Unity Projects\\MatchThemAll - Copy\\Assets\\Match Them All\\Scripts\\Gameplay\\ItemSpotManager.cs", "source_location": "L417", "receiver": null}, {"caller_nid": "gameplay_itemspotmanager_itemspotmanager_getbesthintitems", "callee": "SqrMagnitude", "is_member_call": true, "source_file": "E:\\Unity Projects\\MatchThemAll - Copy\\Assets\\Match Them All\\Scripts\\Gameplay\\ItemSpotManager.cs", "source_location": "L418", "receiver": null}, {"caller_nid": "gameplay_itemspotmanager_itemspotmanager_getbesthintitems", "callee": "GetRange", "is_member_call": true, "source_file": "E:\\Unity Projects\\MatchThemAll - Copy\\Assets\\Match Them All\\Scripts\\Gameplay\\ItemSpotManager.cs", "source_location": "L419", "receiver": null}]}