{"nodes": [{"id": "e_unity_projects_matchthemall_copy_assets_match_them_all_scripts_gameplay_matchsystem_cs", "label": "MatchSystem.cs", "file_type": "code", "source_file": "Gameplay/MatchSystem.cs", "source_location": "L1"}, {"id": "gameplay_matchsystem_matchthemall_scripts", "label": "MatchThemAll.Scripts", "file_type": "code", "source_file": "Gameplay/MatchSystem.cs", "source_location": "L4"}, {"id": "gameplay_matchsystem_matchsystem", "label": "MatchSystem", "file_type": "code", "source_file": "Gameplay/MatchSystem.cs", "source_location": "L6"}, {"id": "monobehaviour", "label": "MonoBehaviour", "file_type": "code", "source_file": "", "source_location": ""}, {"id": "gameplay_matchsystem_matchsystem_awake", "label": ".Awake()", "file_type": "code", "source_file": "Gameplay/MatchSystem.cs", "source_location": "L8"}, {"id": "gameplay_matchsystem_matchsystem_ondestroy", "label": ".OnDestroy()", "file_type": "code", "source_file": "Gameplay/MatchSystem.cs", "source_location": "L10"}, {"id": "gameplay_matchsystem_matchsystem_onitemreachedspot", "label": ".OnItemReachedSpot()", "file_type": "code", "source_file": "Gameplay/MatchSystem.cs", "source_location": "L12"}, {"id": "itemreachedspotevent", "label": "ItemReachedSpotEvent", "file_type": "code", "source_file": "Gameplay/MatchSystem.cs", "source_location": "L12"}], "edges": [{"source": "e_unity_projects_matchthemall_copy_assets_match_them_all_scripts_gameplay_matchsystem_cs", "target": "unityengine", "relation": "imports", "context": "import", "confidence": "EXTRACTED", "source_file": "Gameplay/MatchSystem.cs", "source_location": "L1", "weight": 1.0}, {"source": "e_unity_projects_matchthemall_copy_assets_match_them_all_scripts_gameplay_matchsystem_cs", "target": "zlinq", "relation": "imports", "context": "import", "confidence": "EXTRACTED", "source_file": "Gameplay/MatchSystem.cs", "source_location": "L2", "weight": 1.0}, {"source": "e_unity_projects_matchthemall_copy_assets_match_them_all_scripts_gameplay_matchsystem_cs", "target": "gameplay_matchsystem_matchthemall_scripts", "relation": "contains", "confidence": "EXTRACTED", "source_file": "Gameplay/MatchSystem.cs", "source_location": "L4", "weight": 1.0}, {"source": "e_unity_projects_matchthemall_copy_assets_match_them_all_scripts_gameplay_matchsystem_cs", "target": "gameplay_matchsystem_matchsystem", "relation": "contains", "confidence": "EXTRACTED", "source_file": "Gameplay/MatchSystem.cs", "source_location": "L6", "weight": 1.0}, {"source": "gameplay_matchsystem_matchsystem", "target": "monobehaviour", "relation": "inherits", "confidence": "EXTRACTED", "source_file": "Gameplay/MatchSystem.cs", "source_location": "L6", "weight": 1.0}, {"source": "gameplay_matchsystem_matchsystem", "target": "gameplay_matchsystem_matchsystem_awake", "relation": "method", "confidence": "EXTRACTED", "source_file": "Gameplay/MatchSystem.cs", "source_location": "L8", "weight": 1.0}, {"source": "gameplay_matchsystem_matchsystem", "target": "gameplay_matchsystem_matchsystem_ondestroy", "relation": "method", "confidence": "EXTRACTED", "source_file": "Gameplay/MatchSystem.cs", "source_location": "L10", "weight": 1.0}, {"source": "gameplay_matchsystem_matchsystem", "target": "gameplay_matchsystem_matchsystem_onitemreachedspot", "relation": "method", "confidence": "EXTRACTED", "source_file": "Gameplay/MatchSystem.cs", "source_location": "L12", "weight": 1.0}, {"source": "gameplay_matchsystem_matchsystem_onitemreachedspot", "target": "itemreachedspotevent", "relation": "references", "confidence": "EXTRACTED", "source_file": "Gameplay/MatchSystem.cs", "source_location": "L12", "weight": 1.0, "context": "parameter_type"}], "raw_calls": [{"caller_nid": "gameplay_matchsystem_matchsystem_awake", "callee": "Subscribe<ItemReachedSpotEvent>", "is_member_call": true, "source_file": "E:\\Unity Projects\\MatchThemAll - Copy\\Assets\\Match Them All\\Scripts\\Gameplay\\MatchSystem.cs", "source_location": "L8", "receiver": null}, {"caller_nid": "gameplay_matchsystem_matchsystem_ondestroy", "callee": "Unsubscribe<ItemReachedSpotEvent>", "is_member_call": true, "source_file": "E:\\Unity Projects\\MatchThemAll - Copy\\Assets\\Match Them All\\Scripts\\Gameplay\\MatchSystem.cs", "source_location": "L10", "receiver": null}, {"caller_nid": "gameplay_matchsystem_matchsystem_onitemreachedspot", "callee": "ToList", "is_member_call": true, "source_file": "E:\\Unity Projects\\MatchThemAll - Copy\\Assets\\Match Them All\\Scripts\\Gameplay\\MatchSystem.cs", "source_location": "L17", "receiver": null}, {"caller_nid": "gameplay_matchsystem_matchsystem_onitemreachedspot", "callee": "Take", "is_member_call": true, "source_file": "E:\\Unity Projects\\MatchThemAll - Copy\\Assets\\Match Them All\\Scripts\\Gameplay\\MatchSystem.cs", "source_location": "L17", "receiver": null}, {"caller_nid": "gameplay_matchsystem_matchsystem_onitemreachedspot", "callee": "Where", "is_member_call": true, "source_file": "E:\\Unity Projects\\MatchThemAll - Copy\\Assets\\Match Them All\\Scripts\\Gameplay\\MatchSystem.cs", "source_location": "L17", "receiver": null}, {"caller_nid": "gameplay_matchsystem_matchsystem_onitemreachedspot", "callee": "AsValueEnumerable", "is_member_call": true, "source_file": "E:\\Unity Projects\\MatchThemAll - Copy\\Assets\\Match Them All\\Scripts\\Gameplay\\MatchSystem.cs", "source_location": "L17", "receiver": null}, {"caller_nid": "gameplay_matchsystem_matchsystem_onitemreachedspot", "callee": "GetItemsOnBoard", "is_member_call": true, "source_file": "E:\\Unity Projects\\MatchThemAll - Copy\\Assets\\Match Them All\\Scripts\\Gameplay\\MatchSystem.cs", "source_location": "L17", "receiver": null}, {"caller_nid": "gameplay_matchsystem_matchsystem_onitemreachedspot", "callee": "Publish", "is_member_call": true, "source_file": "E:\\Unity Projects\\MatchThemAll - Copy\\Assets\\Match Them All\\Scripts\\Gameplay\\MatchSystem.cs", "source_location": "L24", "receiver": null}, {"caller_nid": "gameplay_matchsystem_matchsystem_onitemreachedspot", "callee": "IsBoardFullAndNoItemsMoving", "is_member_call": true, "source_file": "E:\\Unity Projects\\MatchThemAll - Copy\\Assets\\Match Them All\\Scripts\\Gameplay\\MatchSystem.cs", "source_location": "L29", "receiver": null}, {"caller_nid": "gameplay_matchsystem_matchsystem_onitemreachedspot", "callee": "Publish", "is_member_call": true, "source_file": "E:\\Unity Projects\\MatchThemAll - Copy\\Assets\\Match Them All\\Scripts\\Gameplay\\MatchSystem.cs", "source_location": "L30", "receiver": null}]}